aqi_hub/__init__.py
aqi_hub/aqi_cn/__init__.py
aqi_hub/aqi_cn/aqi.py
aqi_hub/aqi_cn/common.py
aqi_hub/aqi_usa/__init__.py
aqi_hub/aqi_usa/aqi.py
aqi_hub/aqi_usa/common.py
aqi_hub-0.2.1.dist-info/METADATA
aqi_hub-0.2.1.dist-info/WHEEL
aqi_hub-0.2.1.dist-info/licenses/LICENSE
aqi_hub-0.2.1.dist-info/RECORD
