Metadata-Version: 2.4
Name: aqi-hub
Version: 0.2.1
Summary: Air quality index hub
Project-URL: Homepage, https://github.com/caiyunapp/aqi-hub
Project-URL: Issues, https://github.com/caiyunapp/aqi-hub/issues
Author-email: caiyunapp <oss@caiyunapp.com>, Water Ghost <maxlee1991zyz@gmail.com>, ringsaturn <ringsaturn.me@gmail.com>
Maintainer-email: caiyunapp <oss@caiyunapp.com>, Water Ghost <maxlee1991zyz@gmail.com>, ringsaturn <ringsaturn.me@gmail.com>
License-File: LICENSE
Keywords: air quality,aqi
Requires-Python: >=3.10
